libacbf/__init__.py
libacbf/archivereader.py
libacbf/body.py
libacbf/bookdata.py
libacbf/constants.py
libacbf/exceptions.py
libacbf/helpers.py
libacbf/libacbf.py
libacbf/metadata.py
libacbf/schema/acbf-1.0.xsd
libacbf/schema/acbf-1.1.xsd
libacbf-1.0.2.dist-info/LICENSE
libacbf-1.0.2.dist-info/METADATA
libacbf-1.0.2.dist-info/WHEEL
libacbf-1.0.2.dist-info/top_level.txt
libacbf-1.0.2.dist-info/RECORD
